{
  "picks": [
    {
      "pick_number": 1,
      "round": 1,
      "pick_in_round": 1,
      "team": "Cock N Bulls",
      "owner": "Levi",
      "player_name": "Isiah Pacheco   KC",
      "position": "RB"
    },
    {
      "pick_number": 2,
      "round": 1,
      "pick_in_round": 2,
      "team": "Jodi's Broncos",
      "owner": "Jodi",
      "player_name": "Derrick Henry   BAL",
      "position": "RB"
    },
    {
      "pick_number": 3,
      "round": 1,
      "pick_in_round": 3,
      "team": "Royal Chiefs",
      "owner": "Scott",
      "player_name": "Patrick Mahomes II   KC",
      "position": "QB"
    },
    {
      "pick_number": 4,
      "round": 1,
      "pick_in_round": 4,
      "team": "Hail Mary's",
      "owner": "Mary",
      "player_name": "Amon-Ra St. Brown   DET",
      "position": "WR"
    },
    {
      "pick_number": 5,
      "round": 1,
      "pick_in_round": 5,
      "team": "Lambs",
      "owner": "Adam",
      "player_name": "Tyreek Hill   MIA",
      "position": "WR"
    },
    {
      "pick_number": 6,
      "round": 1,
      "pick_in_round": 6,
      "team": "Brew Crew",
      "owner": "Dan B",
      "player_name": "Christian McCaffrey   SF",
      "position": "RB"
    },
    {
      "pick_number": 7,
      "round": 1,
      "pick_in_round": 7,
      "team": "Champion Boy",
      "owner": "Dan C",
      "player_name": "Justin Jefferson   MIN",
      "position": "WR"
    },
    {
      "pick_number": 8,
      "round": 1,
      "pick_in_round": 8,
      "team": "Crush",
      "owner": "Chuck",
      "player_name": "Saquon Barkley   PHI",
      "position": "RB"
    },
    {
      "pick_number": 9,
      "round": 1,
      "pick_in_round": 9,
      "team": "Brokeback Cowboys",
      "owner": "Kevin",
      "player_name": "CeeDee Lamb   DAL",
      "position": "WR"
    },
    {
      "pick_number": 10,
      "round": 1,
      "pick_in_round": 10,
      "team": "Niner Nation",
      "owner": "Jayden",
      "player_name": "Bijan Robinson   ATL",
      "position": "RB"
    },
    {
      "pick_number": 11,
      "round": 2,
      "pick_in_round": 1,
      "team": "Niner Nation",
      "owner": "Jayden",
      "player_name": "Brock Purdy   SF",
      "position": "QB"
    },
    {
      "pick_number": 12,
      "round": 2,
      "pick_in_round": 2,
      "team": "Brokeback Cowboys",
      "owner": "Kevin",
      "player_name": "Travis Etienne Jr.   JAC",
      "position": "RB"
    },
    {
      "pick_number": 13,
      "round": 2,
      "pick_in_round": 3,
      "team": "Crush",
      "owner": "Chuck",
      "player_name": "Marvin Harrison Jr.   ARI",
      "position": "WR"
    },
    {
      "pick_number": 14,
      "round": 2,
      "pick_in_round": 4,
      "team": "Champion Boy",
      "owner": "Dan C",
      "player_name": "Jonathan Taylor   IND",
      "position": "RB"
    },
    {
      "pick_number": 15,
      "round": 2,
      "pick_in_round": 5,
      "team": "Brew Crew",
      "owner": "Dan B",
      "player_name": "Deebo Samuel Sr.   SF",
      "position": "WR"
    },
    {
      "pick_number": 16,
      "round": 2,
      "pick_in_round": 6,
      "team": "Lambs",
      "owner": "Adam",
      "player_name": "Breece Hall   NYJ",
      "position": "RB"
    },
    {
      "pick_number": 17,
      "round": 2,
      "pick_in_round": 7,
      "team": "Hail Mary's",
      "owner": "Mary",
      "player_name": "Joe Mixon   HOU",
      "position": "RB"
    },
    {
      "pick_number": 18,
      "round": 2,
      "pick_in_round": 8,
      "team": "Royal Chiefs",
      "owner": "Scott",
      "player_name": "J.K. Dobbins   LAC",
      "position": "RB"
    },
    {
      "pick_number": 19,
      "round": 2,
      "pick_in_round": 9,
      "team": "Jodi's Broncos",
      "owner": "Jodi",
      "player_name": "Ja'Marr Chase   CIN",
      "position": "WR"
    },
    {
      "pick_number": 20,
      "round": 2,
      "pick_in_round": 10,
      "team": "Cock N Bulls",
      "owner": "Levi",
      "player_name": "George Kittle   SF",
      "position": "TE"
    },
    {
      "pick_number": 21,
      "round": 3,
      "pick_in_round": 1,
      "team": "Cock N Bulls",
      "owner": "Levi",
      "player_name": "Josh Jacobs   GB",
      "position": "RB"
    },
    {
      "pick_number": 22,
      "round": 3,
      "pick_in_round": 2,
      "team": "Jodi's Broncos",
      "owner": "Jodi",
      "player_name": "Sam LaPorta   DET",
      "position": "TE"
    },
    {
      "pick_number": 23,
      "round": 3,
      "pick_in_round": 3,
      "team": "Royal Chiefs",
      "owner": "Scott",
      "player_name": "Travis Kelce   KC",
      "position": "TE"
    },
    {
      "pick_number": 24,
      "round": 3,
      "pick_in_round": 4,
      "team": "Hail Mary's",
      "owner": "Mary",
      "player_name": "Josh Allen   BUF",
      "position": "QB"
    },
    {
      "pick_number": 25,
      "round": 3,
      "pick_in_round": 5,
      "team": "Lambs",
      "owner": "Adam",
      "player_name": "Mark Andrews   BAL",
      "position": "TE"
    },
    {
      "pick_number": 26,
      "round": 3,
      "pick_in_round": 6,
      "team": "Brew Crew",
      "owner": "Dan B",
      "player_name": "Chris Olave   NO",
      "position": "WR"
    },
    {
      "pick_number": 27,
      "round": 3,
      "pick_in_round": 7,
      "team": "Champion Boy",
      "owner": "Dan C",
      "player_name": "Garrett Wilson   NYJ",
      "position": "WR"
    },
    {
      "pick_number": 28,
      "round": 3,
      "pick_in_round": 8,
      "team": "Crush",
      "owner": "Chuck",
      "player_name": "Nico Collins   HOU",
      "position": "WR"
    },
    {
      "pick_number": 29,
      "round": 3,
      "pick_in_round": 9,
      "team": "Brokeback Cowboys",
      "owner": "Kevin",
      "player_name": "A.J. Brown   PHI",
      "position": "WR"
    },
    {
      "pick_number": 30,
      "round": 3,
      "pick_in_round": 10,
      "team": "Niner Nation",
      "owner": "Jayden",
      "player_name": "Puka Nacua   LAR",
      "position": "WR"
    },
    {
      "pick_number": 31,
      "round": 4,
      "pick_in_round": 1,
      "team": "Niner Nation",
      "owner": "Jayden",
      "player_name": "Davante Adams",
      "position": "WR"
    },
    {
      "pick_number": 32,
      "round": 4,
      "pick_in_round": 2,
      "team": "Brokeback Cowboys",
      "owner": "Kevin",
      "player_name": "Jahmyr Gibbs   DET",
      "position": "RB"
    },
    {
      "pick_number": 33,
      "round": 4,
      "pick_in_round": 3,
      "team": "Crush",
      "owner": "Chuck",
      "player_name": "Brandon Aiyuk   SF",
      "position": "WR"
    },
    {
      "pick_number": 34,
      "round": 4,
      "pick_in_round": 4,
      "team": "Champion Boy",
      "owner": "Dan C",
      "player_name": "Jalen Hurts   PHI",
      "position": "QB"
    },
    {
      "pick_number": 35,
      "round": 4,
      "pick_in_round": 5,
      "team": "Brew Crew",
      "owner": "Dan B",
      "player_name": "Lamar Jackson   BAL",
      "position": "QB"
    },
    {
      "pick_number": 36,
      "round": 4,
      "pick_in_round": 6,
      "team": "Lambs",
      "owner": "Adam",
      "player_name": "Kyren Williams   LAR",
      "position": "RB"
    },
    {
      "pick_number": 37,
      "round": 4,
      "pick_in_round": 7,
      "team": "Hail Mary's",
      "owner": "Mary",
      "player_name": "Drake London   ATL",
      "position": "WR"
    },
    {
      "pick_number": 38,
      "round": 4,
      "pick_in_round": 8,
      "team": "Royal Chiefs",
      "owner": "Scott",
      "player_name": "Alvin Kamara   NO",
      "position": "RB"
    },
    {
      "pick_number": 39,
      "round": 4,
      "pick_in_round": 9,
      "team": "Jodi's Broncos",
      "owner": "Jodi",
      "player_name": "Mike Evans   TB",
      "position": "WR"
    },
    {
      "pick_number": 40,
      "round": 4,
      "pick_in_round": 10,
      "team": "Cock N Bulls",
      "owner": "Levi",
      "player_name": "Tua Tagovailoa   MIA",
      "position": "QB"
    },
    {
      "pick_number": 41,
      "round": 5,
      "pick_in_round": 1,
      "team": "Cock N Bulls",
      "owner": "Levi",
      "player_name": "Jaylen Waddle   MIA",
      "position": "WR"
    },
    {
      "pick_number": 42,
      "round": 5,
      "pick_in_round": 2,
      "team": "Jodi's Broncos",
      "owner": "Jodi",
      "player_name": "Joe Burrow   CIN",
      "position": "QB"
    },
    {
      "pick_number": 43,
      "round": 5,
      "pick_in_round": 3,
      "team": "Royal Chiefs",
      "owner": "Scott",
      "player_name": "D'Andre Swift   CHI",
      "position": "RB"
    },
    {
      "pick_number": 44,
      "round": 5,
      "pick_in_round": 4,
      "team": "Hail Mary's",
      "owner": "Mary",
      "player_name": "Rachaad White   TB",
      "position": "RB"
    },
    {
      "pick_number": 45,
      "round": 5,
      "pick_in_round": 5,
      "team": "Lambs",
      "owner": "Adam",
      "player_name": "Kenneth Walker III   SEA",
      "position": "RB"
    },
    {
      "pick_number": 46,
      "round": 5,
      "pick_in_round": 6,
      "team": "Brew Crew",
      "owner": "Dan B",
      "player_name": "DJ Moore -  CHI",
      "position": "WR"
    },
    {
      "pick_number": 47,
      "round": 5,
      "pick_in_round": 7,
      "team": "Champion Boy",
      "owner": "Dan C",
      "player_name": "Cooper Kupp - LAR",
      "position": "WR"
    },
    {
      "pick_number": 48,
      "round": 5,
      "pick_in_round": 8,
      "team": "Crush",
      "owner": "Chuck",
      "player_name": "De'Von Achane   MIA",
      "position": "RB"
    },
    {
      "pick_number": 49,
      "round": 5,
      "pick_in_round": 9,
      "team": "Brokeback Cowboys",
      "owner": "Kevin",
      "player_name": "James Cook   BUF",
      "position": "RB"
    },
    {
      "pick_number": 50,
      "round": 5,
      "pick_in_round": 10,
      "team": "Niner Nation",
      "owner": "Jayden",
      "player_name": "DK Metcalf   SEA",
      "position": "WR"
    },
    {
      "pick_number": 51,
      "round": 6,
      "pick_in_round": 1,
      "team": "Niner Nation",
      "owner": "Jayden",
      "player_name": "Stefon Diggs  - HOU",
      "position": "WR"
    },
    {
      "pick_number": 52,
      "round": 6,
      "pick_in_round": 2,
      "team": "Brokeback Cowboys",
      "owner": "Kevin",
      "player_name": "Michael Pittman Jr.   IND",
      "position": "WR"
    },
    {
      "pick_number": 53,
      "round": 6,
      "pick_in_round": 3,
      "team": "Crush",
      "owner": "Chuck",
      "player_name": "Kyler Murray   ARI",
      "position": "QB"
    },
    {
      "pick_number": 54,
      "round": 6,
      "pick_in_round": 4,
      "team": "Champion Boy",
      "owner": "Dan C",
      "player_name": "Kyle Pitts   ATL",
      "position": "TE"
    },
    {
      "pick_number": 55,
      "round": 6,
      "pick_in_round": 5,
      "team": "Brew Crew",
      "owner": "Dan B",
      "player_name": "Najee Harris   PIT",
      "position": "RB"
    },
    {
      "pick_number": 56,
      "round": 6,
      "pick_in_round": 6,
      "team": "Lambs",
      "owner": "Adam",
      "player_name": "Dak Prescott   DAL",
      "position": "QB"
    },
    {
      "pick_number": 57,
      "round": 6,
      "pick_in_round": 7,
      "team": "Hail Mary's",
      "owner": "Mary",
      "player_name": "Dalton Kincaid  - BUF",
      "position": "TE"
    },
    {
      "pick_number": 58,
      "round": 6,
      "pick_in_round": 8,
      "team": "Royal Chiefs",
      "owner": "Scott",
      "player_name": "Cole Kmet - CHI",
      "position": "TE"
    },
    {
      "pick_number": 59,
      "round": 6,
      "pick_in_round": 9,
      "team": "Jodi's Broncos",
      "owner": "Jodi",
      "player_name": "James Conner -  ARI",
      "position": "RB"
    },
    {
      "pick_number": 60,
      "round": 6,
      "pick_in_round": 10,
      "team": "Cock N Bulls",
      "owner": "Levi",
      "player_name": "Raheem Mostert -  MIA",
      "position": "RB"
    },
    {
      "pick_number": 61,
      "round": 7,
      "pick_in_round": 1,
      "team": "Cock N Bulls",
      "owner": "Levi",
      "player_name": "San Francisco 49ers - SF",
      "position": "DST"
    },
    {
      "pick_number": 62,
      "round": 7,
      "pick_in_round": 2,
      "team": "Jodi's Broncos",
      "owner": "Jodi",
      "player_name": "C.J. Stroud   HOU",
      "position": "QB"
    },
    {
      "pick_number": 63,
      "round": 7,
      "pick_in_round": 3,
      "team": "Royal Chiefs",
      "owner": "Scott",
      "player_name": "Javonte Williams - DEN",
      "position": "RB"
    },
    {
      "pick_number": 64,
      "round": 7,
      "pick_in_round": 4,
      "team": "Hail Mary's",
      "owner": "Mary",
      "player_name": "Malik Nabers   NYG",
      "position": "WR"
    },
    {
      "pick_number": 65,
      "round": 7,
      "pick_in_round": 5,
      "team": "Lambs",
      "owner": "Adam",
      "player_name": "DeVonta Smith   PHI",
      "position": "WR"
    },
    {
      "pick_number": 66,
      "round": 7,
      "pick_in_round": 6,
      "team": "Brew Crew",
      "owner": "Dan B",
      "player_name": "Aaron Jones   MIN",
      "position": "RB"
    },
    {
      "pick_number": 67,
      "round": 7,
      "pick_in_round": 7,
      "team": "Champion Boy",
      "owner": "Dan C",
      "player_name": "Rhamondre Stevenson   NE",
      "position": "RB"
    },
    {
      "pick_number": 68,
      "round": 7,
      "pick_in_round": 8,
      "team": "Crush",
      "owner": "Chuck",
      "player_name": "David Montgomery   DET",
      "position": "RB"
    },
    {
      "pick_number": 69,
      "round": 7,
      "pick_in_round": 9,
      "team": "Brokeback Cowboys",
      "owner": "Kevin",
      "player_name": "Jordan Love   GB",
      "position": "QB"
    },
    {
      "pick_number": 70,
      "round": 7,
      "pick_in_round": 10,
      "team": "Niner Nation",
      "owner": "Jayden",
      "player_name": "Baltimore Ravens   BAL",
      "position": "DST"
    },
    {
      "pick_number": 71,
      "round": 8,
      "pick_in_round": 1,
      "team": "Niner Nation",
      "owner": "Jayden",
      "player_name": "Ezekiel Elliott - DAL",
      "position": "RB"
    },
    {
      "pick_number": 72,
      "round": 8,
      "pick_in_round": 2,
      "team": "Brokeback Cowboys",
      "owner": "Kevin",
      "player_name": "Zamir White - LV",
      "position": "RB"
    },
    {
      "pick_number": 73,
      "round": 8,
      "pick_in_round": 3,
      "team": "Crush",
      "owner": "Chuck",
      "player_name": "Anthony Richardson - IND",
      "position": "QB"
    },
    {
      "pick_number": 74,
      "round": 8,
      "pick_in_round": 4,
      "team": "Champion Boy",
      "owner": "Dan C",
      "player_name": "Rashee Rice - KC",
      "position": "WR"
    },
    {
      "pick_number": 75,
      "round": 8,
      "pick_in_round": 5,
      "team": "Brew Crew",
      "owner": "Dan B",
      "player_name": "Evan Engram - JAC",
      "position": "TE"
    },
    {
      "pick_number": 76,
      "round": 8,
      "pick_in_round": 6,
      "team": "Lambs",
      "owner": "Adam",
      "player_name": "Zay Flowers - BAL",
      "position": "WR"
    },
    {
      "pick_number": 77,
      "round": 8,
      "pick_in_round": 7,
      "team": "Hail Mary's",
      "owner": "Mary",
      "player_name": "Trey McBride   ARI",
      "position": "TE"
    },
    {
      "pick_number": 78,
      "round": 8,
      "pick_in_round": 8,
      "team": "Royal Chiefs",
      "owner": "Scott",
      "player_name": "Rome Odunze   CHI",
      "position": "WR"
    },
    {
      "pick_number": 79,
      "round": 8,
      "pick_in_round": 9,
      "team": "Jodi's Broncos",
      "owner": "Jodi",
      "player_name": "Tee Higgins   CIN",
      "position": "WR"
    },
    {
      "pick_number": 80,
      "round": 8,
      "pick_in_round": 10,
      "team": "Cock N Bulls",
      "owner": "Levi",
      "player_name": "Jared Goff   DET",
      "position": "QB"
    },
    {
      "pick_number": 81,
      "round": 9,
      "pick_in_round": 1,
      "team": "Cock N Bulls",
      "owner": "Levi",
      "player_name": "Keenan Allen   CHI",
      "position": "WR"
    },
    {
      "pick_number": 82,
      "round": 9,
      "pick_in_round": 2,
      "team": "Jodi's Broncos",
      "owner": "Jodi",
      "player_name": "Jerome Ford   CLE",
      "position": "RB"
    },
    {
      "pick_number": 83,
      "round": 9,
      "pick_in_round": 3,
      "team": "Royal Chiefs",
      "owner": "Scott",
      "player_name": "Bo Nix   DEN",
      "position": "QB"
    },
    {
      "pick_number": 84,
      "round": 9,
      "pick_in_round": 4,
      "team": "Hail Mary's",
      "owner": "Mary",
      "player_name": "Jonathon Brooks   CAR",
      "position": "RB"
    },
    {
      "pick_number": 85,
      "round": 9,
      "pick_in_round": 5,
      "team": "Lambs",
      "owner": "Adam",
      "player_name": "Trevor Lawrence - JAC",
      "position": "QB"
    },
    {
      "pick_number": 86,
      "round": 9,
      "pick_in_round": 6,
      "team": "Brew Crew",
      "owner": "Dan B",
      "player_name": "Tank Dell   HOU",
      "position": "WR"
    },
    {
      "pick_number": 87,
      "round": 9,
      "pick_in_round": 7,
      "team": "Champion Boy",
      "owner": "Dan C",
      "player_name": "Tony Pollard   TEN",
      "position": "RB"
    },
    {
      "pick_number": 88,
      "round": 9,
      "pick_in_round": 8,
      "team": "Crush",
      "owner": "Chuck",
      "player_name": "George Pickens   PIT",
      "position": "WR"
    },
    {
      "pick_number": 89,
      "round": 9,
      "pick_in_round": 9,
      "team": "Brokeback Cowboys",
      "owner": "Kevin",
      "player_name": "Xavier Worthy   KC",
      "position": "WR"
    },
    {
      "pick_number": 90,
      "round": 9,
      "pick_in_round": 10,
      "team": "Niner Nation",
      "owner": "Jayden",
      "player_name": "Nick Chubb   CLE",
      "position": "RB"
    },
    {
      "pick_number": 91,
      "round": 10,
      "pick_in_round": 1,
      "team": "Niner Nation",
      "owner": "Jayden",
      "player_name": "Justin Herbert   LAC",
      "position": "QB"
    },
    {
      "pick_number": 92,
      "round": 10,
      "pick_in_round": 2,
      "team": "Brokeback Cowboys",
      "owner": "Kevin",
      "player_name": "Jake Ferguson - DAL",
      "position": "TE"
    },
    {
      "pick_number": 93,
      "round": 10,
      "pick_in_round": 3,
      "team": "Crush",
      "owner": "Chuck",
      "player_name": "Brian Robinson Jr.   WAS",
      "position": "RB"
    },
    {
      "pick_number": 94,
      "round": 10,
      "pick_in_round": 4,
      "team": "Champion Boy",
      "owner": "Dan C",
      "player_name": "Jayden Daniels   WAS",
      "position": "QB"
    },
    {
      "pick_number": 95,
      "round": 10,
      "pick_in_round": 5,
      "team": "Brew Crew",
      "owner": "Dan B",
      "player_name": "New York Jets   NYJ",
      "position": "DST"
    },
    {
      "pick_number": 96,
      "round": 10,
      "pick_in_round": 6,
      "team": "Lambs",
      "owner": "Adam",
      "player_name": "Zack Moss   CIN",
      "position": "RB"
    },
    {
      "pick_number": 97,
      "round": 10,
      "pick_in_round": 7,
      "team": "Hail Mary's",
      "owner": "Mary",
      "player_name": "Justin Tucker   BAL",
      "position": "K"
    },
    {
      "pick_number": 98,
      "round": 10,
      "pick_in_round": 8,
      "team": "Royal Chiefs",
      "owner": "Scott",
      "player_name": "Chris Godwin   TB",
      "position": "WR"
    },
    {
      "pick_number": 99,
      "round": 10,
      "pick_in_round": 9,
      "team": "Jodi's Broncos",
      "owner": "Jodi",
      "player_name": "Amari Cooper   CLE",
      "position": "WR"
    },
    {
      "pick_number": 100,
      "round": 10,
      "pick_in_round": 10,
      "team": "Cock N Bulls",
      "owner": "Levi",
      "player_name": "Terry McLaurin   WAS",
      "position": "WR"
    },
    {
      "pick_number": 101,
      "round": 11,
      "pick_in_round": 1,
      "team": "Cock N Bulls",
      "owner": "Levi",
      "player_name": "Tyler Bass   BUF",
      "position": "K"
    },
    {
      "pick_number": 102,
      "round": 11,
      "pick_in_round": 2,
      "team": "Jodi's Broncos",
      "owner": "Jodi",
      "player_name": "Courtland Sutton   DEN",
      "position": "WR"
    },
    {
      "pick_number": 103,
      "round": 11,
      "pick_in_round": 3,
      "team": "Royal Chiefs",
      "owner": "Scott",
      "player_name": "Jaxon Smith-Njigba   SEA",
      "position": "WR"
    },
    {
      "pick_number": 104,
      "round": 11,
      "pick_in_round": 4,
      "team": "Hail Mary's",
      "owner": "Mary",
      "player_name": "Dallas Cowboys   DAL",
      "position": "DST"
    },
    {
      "pick_number": 105,
      "round": 11,
      "pick_in_round": 5,
      "team": "Lambs",
      "owner": "Adam",
      "player_name": "Keon Coleman   BUF",
      "position": "WR"
    },
    {
      "pick_number": 106,
      "round": 11,
      "pick_in_round": 6,
      "team": "Brew Crew",
      "owner": "Dan B",
      "player_name": "Brock Bowers   LV",
      "position": "TE"
    },
    {
      "pick_number": 107,
      "round": 11,
      "pick_in_round": 7,
      "team": "Champion Boy",
      "owner": "Dan C",
      "player_name": "Calvin Ridley   TEN",
      "position": "WR"
    },
    {
      "pick_number": 108,
      "round": 11,
      "pick_in_round": 8,
      "team": "Crush",
      "owner": "Chuck",
      "player_name": "Christian Watson   GB",
      "position": "WR"
    },
    {
      "pick_number": 109,
      "round": 11,
      "pick_in_round": 9,
      "team": "Brokeback Cowboys",
      "owner": "Kevin",
      "player_name": "Brandon Aubrey   DAL",
      "position": "K"
    },
    {
      "pick_number": 110,
      "round": 11,
      "pick_in_round": 10,
      "team": "Niner Nation",
      "owner": "Jayden",
      "player_name": "Jake Moody   SF",
      "position": "K"
    },
    {
      "pick_number": 111,
      "round": 12,
      "pick_in_round": 1,
      "team": "Niner Nation",
      "owner": "Jayden",
      "player_name": "David Njoku   CLE",
      "position": "TE"
    },
    {
      "pick_number": 112,
      "round": 12,
      "pick_in_round": 2,
      "team": "Brokeback Cowboys",
      "owner": "Kevin",
      "player_name": "Kansas City Chiefs   KC",
      "position": "DST"
    },
    {
      "pick_number": 113,
      "round": 12,
      "pick_in_round": 3,
      "team": "Crush",
      "owner": "Chuck",
      "player_name": "Dallas Goedert   PHI",
      "position": "TE"
    },
    {
      "pick_number": 114,
      "round": 12,
      "pick_in_round": 4,
      "team": "Champion Boy",
      "owner": "Dan C",
      "player_name": "Chase Brown   CIN",
      "position": "RB"
    },
    {
      "pick_number": 115,
      "round": 12,
      "pick_in_round": 5,
      "team": "Brew Crew",
      "owner": "Dan B",
      "player_name": "Matthew Stafford   LAR",
      "position": "QB"
    },
    {
      "pick_number": 116,
      "round": 12,
      "pick_in_round": 6,
      "team": "Lambs",
      "owner": "Adam",
      "player_name": "Austin Ekeler   WAS",
      "position": "RB"
    },
    {
      "pick_number": 117,
      "round": 12,
      "pick_in_round": 7,
      "team": "Hail Mary's",
      "owner": "Mary",
      "player_name": "Caleb Williams   CHI",
      "position": "QB"
    },
    {
      "pick_number": 118,
      "round": 12,
      "pick_in_round": 8,
      "team": "Royal Chiefs",
      "owner": "Scott",
      "player_name": "Harrison Butker   KC",
      "position": "K"
    },
    {
      "pick_number": 119,
      "round": 12,
      "pick_in_round": 9,
      "team": "Jodi's Broncos",
      "owner": "Jodi",
      "player_name": "Gus Edwards   LAC",
      "position": "RB"
    },
    {
      "pick_number": 120,
      "round": 12,
      "pick_in_round": 10,
      "team": "Cock N Bulls",
      "owner": "Levi",
      "player_name": "DeAndre Hopkins   TEN",
      "position": "WR"
    },
    {
      "pick_number": 121,
      "round": 13,
      "pick_in_round": 1,
      "team": "Cock N Bulls",
      "owner": "Levi",
      "player_name": "Dalton Schultz   HOU",
      "position": "TE"
    },
    {
      "pick_number": 122,
      "round": 13,
      "pick_in_round": 2,
      "team": "Jodi's Broncos",
      "owner": "Jodi",
      "player_name": "Cleveland Browns   CLE",
      "position": "DST"
    },
    {
      "pick_number": 123,
      "round": 13,
      "pick_in_round": 3,
      "team": "Royal Chiefs",
      "owner": "Scott",
      "player_name": "Detroit Lions   DET",
      "position": "DST"
    },
    {
      "pick_number": 124,
      "round": 13,
      "pick_in_round": 4,
      "team": "Hail Mary's",
      "owner": "Mary",
      "player_name": "Jordan Addison   MIN",
      "position": "WR"
    },
    {
      "pick_number": 125,
      "round": 13,
      "pick_in_round": 5,
      "team": "Lambs",
      "owner": "Adam",
      "player_name": "Buffalo Bills   BUF",
      "position": "DST"
    },
    {
      "pick_number": 126,
      "round": 13,
      "pick_in_round": 6,
      "team": "Brew Crew",
      "owner": "Dan B",
      "player_name": "Chuba Hubbard   CAR",
      "position": "rb"
    },
    {
      "pick_number": 127,
      "round": 13,
      "pick_in_round": 7,
      "team": "Champion Boy",
      "owner": "Dan C",
      "player_name": "Pittsburgh Steelers   PIT",
      "position": "DST"
    },
    {
      "pick_number": 128,
      "round": 13,
      "pick_in_round": 8,
      "team": "Crush",
      "owner": "Chuck",
      "player_name": "Christian Kirk   JAC",
      "position": "WR"
    },
    {
      "pick_number": 129,
      "round": 13,
      "pick_in_round": 9,
      "team": "Brokeback Cowboys",
      "owner": "Kevin",
      "player_name": "Aaron Rodgers   NYJ",
      "position": "QB"
    },
    {
      "pick_number": 130,
      "round": 13,
      "pick_in_round": 10,
      "team": "Niner Nation",
      "owner": "Jayden",
      "player_name": "Jaylen Warren   PIT",
      "position": "RB"
    },
    {
      "pick_number": 131,
      "round": 14,
      "pick_in_round": 1,
      "team": "Niner Nation",
      "owner": "Jayden",
      "player_name": "Jayden Reed   GB",
      "position": "WR"
    },
    {
      "pick_number": 132,
      "round": 14,
      "pick_in_round": 2,
      "team": "Brokeback Cowboys",
      "owner": "Kevin",
      "player_name": "Taysom Hill   NO",
      "position": "TE"
    },
    {
      "pick_number": 133,
      "round": 14,
      "pick_in_round": 3,
      "team": "Crush",
      "owner": "Chuck",
      "player_name": "Tyjae Spears   TEN",
      "position": "RB"
    },
    {
      "pick_number": 134,
      "round": 14,
      "pick_in_round": 4,
      "team": "Champion Boy",
      "owner": "Dan C",
      "player_name": "Blake Corum   LAR",
      "position": "RB"
    },
    {
      "pick_number": 135,
      "round": 14,
      "pick_in_round": 5,
      "team": "Brew Crew",
      "owner": "Dan B",
      "player_name": "Diontae Johnson   CAR",
      "position": "WR"
    },
    {
      "pick_number": 136,
      "round": 14,
      "pick_in_round": 6,
      "team": "Lambs",
      "owner": "Adam",
      "player_name": "Zach Charbonnet   SEA",
      "position": "RB"
    },
    {
      "pick_number": 137,
      "round": 14,
      "pick_in_round": 7,
      "team": "Hail Mary's",
      "owner": "Mary",
      "player_name": "Trey Benson   ARI",
      "position": "RB"
    },
    {
      "pick_number": 138,
      "round": 14,
      "pick_in_round": 8,
      "team": "Royal Chiefs",
      "owner": "Scott",
      "player_name": "Hollywood Brown   KC",
      "position": "WR"
    },
    {
      "pick_number": 139,
      "round": 14,
      "pick_in_round": 9,
      "team": "Jodi's Broncos",
      "owner": "Jodi",
      "player_name": "Devin Singletary   NYG",
      "position": "RB"
    },
    {
      "pick_number": 140,
      "round": 14,
      "pick_in_round": 10,
      "team": "Cock N Bulls",
      "owner": "Levi",
      "player_name": "Mike Williams   NYJ",
      "position": "WR"
    },
    {
      "pick_number": 141,
      "round": 15,
      "pick_in_round": 1,
      "team": "Cock N Bulls",
      "owner": "Levi",
      "player_name": "MarShawn Lloyd   GB",
      "position": "RB"
    },
    {
      "pick_number": 142,
      "round": 15,
      "pick_in_round": 2,
      "team": "Jodi's Broncos",
      "owner": "Jodi",
      "player_name": "Khalil Shakir   BUF",
      "position": "WR"
    },
    {
      "pick_number": 143,
      "round": 15,
      "pick_in_round": 3,
      "team": "Royal Chiefs",
      "owner": "Scott",
      "player_name": "Bucky Irving   TB",
      "position": "RB"
    },
    {
      "pick_number": 144,
      "round": 15,
      "pick_in_round": 4,
      "team": "Hail Mary's",
      "owner": "Mary",
      "player_name": "Brian Thomas Jr.   JAC",
      "position": "WR"
    },
    {
      "pick_number": 145,
      "round": 15,
      "pick_in_round": 5,
      "team": "Lambs",
      "owner": "Adam",
      "player_name": "Rico Dowdle   DAL",
      "position": "RB"
    },
    {
      "pick_number": 146,
      "round": 15,
      "pick_in_round": 6,
      "team": "Brew Crew",
      "owner": "Dan B",
      "player_name": "Ty Chandler   MIN",
      "position": "RB"
    },
    {
      "pick_number": 147,
      "round": 15,
      "pick_in_round": 7,
      "team": "Champion Boy",
      "owner": "Dan C",
      "player_name": "Jameson Williams   DET",
      "position": "WR"
    },
    {
      "pick_number": 148,
      "round": 15,
      "pick_in_round": 8,
      "team": "Crush",
      "owner": "Chuck",
      "player_name": "Tyler Allgeier   ATL",
      "position": "RB"
    },
    {
      "pick_number": 149,
      "round": 15,
      "pick_in_round": 9,
      "team": "Brokeback Cowboys",
      "owner": "Kevin",
      "player_name": "Ladd McConkey   LAC",
      "position": "WR"
    },
    {
      "pick_number": 150,
      "round": 15,
      "pick_in_round": 10,
      "team": "Niner Nation",
      "owner": "Jayden",
      "player_name": "Pat Freiermuth   PIT",
      "position": "TE"
    },
    {
      "pick_number": 151,
      "round": 16,
      "pick_in_round": 1,
      "team": "Niner Nation",
      "owner": "Jayden",
      "player_name": "Khalil Herbert   CHI",
      "position": "RB"
    },
    {
      "pick_number": 152,
      "round": 16,
      "pick_in_round": 2,
      "team": "Brokeback Cowboys",
      "owner": "Kevin",
      "player_name": "Tank Bigsby   JAC",
      "position": "RB"
    },
    {
      "pick_number": 153,
      "round": 16,
      "pick_in_round": 3,
      "team": "Crush",
      "owner": "Chuck",
      "player_name": "Jake Elliott   PHI",
      "position": "K"
    },
    {
      "pick_number": 154,
      "round": 16,
      "pick_in_round": 4,
      "team": "Champion Boy",
      "owner": "Dan C",
      "player_name": "Luke Musgrave   GB",
      "position": "TE"
    },
    {
      "pick_number": 155,
      "round": 16,
      "pick_in_round": 5,
      "team": "Brew Crew",
      "owner": "Dan B",
      "player_name": "Younghoe Koo   ATL",
      "position": "K"
    },
    {
      "pick_number": 156,
      "round": 16,
      "pick_in_round": 6,
      "team": "Lambs",
      "owner": "Adam",
      "player_name": "Cameron Dicker   LAC",
      "position": "K"
    },
    {
      "pick_number": 157,
      "round": 16,
      "pick_in_round": 7,
      "team": "Hail Mary's",
      "owner": "Mary",
      "player_name": "Kendre Miller   NO",
      "position": "RB"
    },
    {
      "pick_number": 158,
      "round": 16,
      "pick_in_round": 8,
      "team": "Royal Chiefs",
      "owner": "Scott",
      "player_name": "Ju-Ju",
      "position": "WR"
    },
    {
      "pick_number": 159,
      "round": 16,
      "pick_in_round": 9,
      "team": "Jodi's Broncos",
      "owner": "Jodi",
      "player_name": "Jaleel McLaughlin   DEN",
      "position": "RB"
    },
    {
      "pick_number": 160,
      "round": 16,
      "pick_in_round": 10,
      "team": "Cock N Bulls",
      "owner": "Levi",
      "player_name": "Jordan Mason",
      "position": "RB"
    },
    {
      "pick_number": 161,
      "round": 17,
      "pick_in_round": 1,
      "team": "Cock N Bulls",
      "owner": "Levi",
      "player_name": "Jakobi Meyers   LV",
      "position": "WR"
    },
    {
      "pick_number": 162,
      "round": 17,
      "pick_in_round": 2,
      "team": "Jodi's Broncos",
      "owner": "Jodi",
      "player_name": "T.J. Hockenson   MIN",
      "position": "TE"
    },
    {
      "pick_number": 163,
      "round": 17,
      "pick_in_round": 3,
      "team": "Royal Chiefs",
      "owner": "Scott",
      "player_name": "Troy Franklin",
      "position": "WR"
    },
    {
      "pick_number": 164,
      "round": 17,
      "pick_in_round": 4,
      "team": "Hail Mary's",
      "owner": "Mary",
      "player_name": "Houston Texans   HOU",
      "position": "DST"
    },
    {
      "pick_number": 165,
      "round": 17,
      "pick_in_round": 5,
      "team": "Lambs",
      "owner": "Adam",
      "player_name": "Ray Davis   BUF",
      "position": "RB"
    },
    {
      "pick_number": 166,
      "round": 17,
      "pick_in_round": 6,
      "team": "Brew Crew",
      "owner": "Dan B",
      "player_name": "Kendrick Bourne - NE",
      "position": "WR"
    },
    {
      "pick_number": 167,
      "round": 17,
      "pick_in_round": 7,
      "team": "Champion Boy",
      "owner": "Dan C",
      "player_name": "Ka'imi Fairbairn - HOU",
      "position": "K"
    },
    {
      "pick_number": 168,
      "round": 17,
      "pick_in_round": 8,
      "team": "Crush",
      "owner": "Chuck",
      "player_name": "Romeo Doubs - GB",
      "position": "WR"
    },
    {
      "pick_number": 169,
      "round": 17,
      "pick_in_round": 9,
      "team": "Brokeback Cowboys",
      "owner": "Kevin",
      "player_name": "Justice Hill   BAL",
      "position": "RB"
    },
    {
      "pick_number": 170,
      "round": 17,
      "pick_in_round": 10,
      "team": "Niner Nation",
      "owner": "Jayden",
      "player_name": "Tyler Lockett   SEA",
      "position": "WR"
    },
    {
      "pick_number": 171,
      "round": 18,
      "pick_in_round": 1,
      "team": "Niner Nation",
      "owner": "Jayden",
      "player_name": "Odell Beckham Jr.   MIA",
      "position": "WR"
    },
    {
      "pick_number": 172,
      "round": 18,
      "pick_in_round": 2,
      "team": "Brokeback Cowboys",
      "owner": "Kevin",
      "player_name": "Philadelphia Eagles   PHI",
      "position": "DST"
    },
    {
      "pick_number": 173,
      "round": 18,
      "pick_in_round": 3,
      "team": "Crush",
      "owner": "Chuck",
      "player_name": "New Orleans Saints - NO",
      "position": "DST"
    },
    {
      "pick_number": 174,
      "round": 18,
      "pick_in_round": 4,
      "team": "Champion Boy",
      "owner": "Dan C",
      "player_name": "Gabe Davis - JAC",
      "position": "WR"
    },
    {
      "pick_number": 175,
      "round": 18,
      "pick_in_round": 5,
      "team": "Brew Crew",
      "owner": "Dan B",
      "player_name": "Rashid Shaheed   NO",
      "position": "WR"
    },
    {
      "pick_number": 176,
      "round": 18,
      "pick_in_round": 6,
      "team": "Lambs",
      "owner": "Adam",
      "player_name": "Darnell Mooney   ATL",
      "position": "WR"
    },
    {
      "pick_number": 177,
      "round": 18,
      "pick_in_round": 7,
      "team": "Hail Mary's",
      "owner": "Mary",
      "player_name": "Antonio Gibson   NE",
      "position": "RB"
    },
    {
      "pick_number": 178,
      "round": 18,
      "pick_in_round": 8,
      "team": "Royal Chiefs",
      "owner": "Scott",
      "player_name": "Isaiah Likely   BAL",
      "position": "TE"
    },
    {
      "pick_number": 179,
      "round": 18,
      "pick_in_round": 9,
      "team": "Jodi's Broncos",
      "owner": "Jodi",
      "player_name": "Adonai Mitchell   IND",
      "position": "WR"
    },
    {
      "pick_number": 180,
      "round": 18,
      "pick_in_round": 10,
      "team": "Cock N Bulls",
      "owner": "Levi",
      "player_name": "Brandin Cooks   DAL",
      "position": "WR"
    },
    {
      "pick_number": 181,
      "round": 19,
      "pick_in_round": 1,
      "team": "Cock N Bulls",
      "owner": "Levi",
      "player_name": "Samaje Perine   DEN",
      "position": "RB"
    },
    {
      "pick_number": 182,
      "round": 19,
      "pick_in_round": 2,
      "team": "Jodi's Broncos",
      "owner": "Jodi",
      "player_name": "Evan McPherson   CIN",
      "position": "K"
    },
    {
      "pick_number": 183,
      "round": 19,
      "pick_in_round": 3,
      "team": "Royal Chiefs",
      "owner": "Scott",
      "player_name": "Justin Fields   PIT",
      "position": "QB"
    },
    {
      "pick_number": 184,
      "round": 19,
      "pick_in_round": 4,
      "team": "Hail Mary's",
      "owner": "Mary",
      "player_name": "Joshua Palmer - LAC",
      "position": "WR"
    },
    {
      "pick_number": 185,
      "round": 19,
      "pick_in_round": 5,
      "team": "Lambs",
      "owner": "Adam",
      "player_name": "Quentin Johnston - LAC",
      "position": "WR"
    },
    {
      "pick_number": 186,
      "round": 19,
      "pick_in_round": 6,
      "team": "Brew Crew",
      "owner": "Dan B",
      "player_name": "Ricky Pearsall   SF",
      "position": "WR"
    },
    {
      "pick_number": 187,
      "round": 19,
      "pick_in_round": 7,
      "team": "Champion Boy",
      "owner": "Dan C",
      "player_name": "Jaylen Wright   MIA",
      "position": "RB"
    },
    {
      "pick_number": 188,
      "round": 19,
      "pick_in_round": 8,
      "team": "Crush",
      "owner": "Chuck",
      "player_name": "Chigoziem Okonkwo   TEN",
      "position": "TE"
    },
    {
      "pick_number": 189,
      "round": 19,
      "pick_in_round": 9,
      "team": "Brokeback Cowboys",
      "owner": "Kevin",
      "player_name": "Alexander Mattison   LV",
      "position": "RB"
    },
    {
      "pick_number": 190,
      "round": 19,
      "pick_in_round": 10,
      "team": "Niner Nation",
      "owner": "Jayden",
      "player_name": "Clyde Edwards-Helaire   KC",
      "position": "RB"
    }
  ],
  "current_pick": 191,
  "teams": [
    {
      "team_number": 1,
      "owner": "Levi",
      "team_name": "Cock N Bulls",
      "player_col": 1,
      "position_col": 2
    },
    {
      "team_number": 2,
      "owner": "Jodi",
      "team_name": "Jodi's Broncos",
      "player_col": 3,
      "position_col": 4
    },
    {
      "team_number": 3,
      "owner": "Scott",
      "team_name": "Royal Chiefs",
      "player_col": 5,
      "position_col": 6
    },
    {
      "team_number": 4,
      "owner": "Mary",
      "team_name": "Hail Mary's",
      "player_col": 7,
      "position_col": 8
    },
    {
      "team_number": 5,
      "owner": "Adam",
      "team_name": "Lambs",
      "player_col": 9,
      "position_col": 10
    },
    {
      "team_number": 6,
      "owner": "Dan B",
      "team_name": "Brew Crew",
      "player_col": 11,
      "position_col": 12
    },
    {
      "team_number": 7,
      "owner": "Dan C",
      "team_name": "Champion Boy",
      "player_col": 13,
      "position_col": 14
    },
    {
      "team_number": 8,
      "owner": "Chuck",
      "team_name": "Crush",
      "player_col": 15,
      "position_col": 16
    },
    {
      "team_number": 9,
      "owner": "Kevin",
      "team_name": "Brokeback Cowboys",
      "player_col": 17,
      "position_col": 18
    },
    {
      "team_number": 10,
      "owner": "Jayden",
      "team_name": "Niner Nation",
      "player_col": 19,
      "position_col": 20
    }
  ],
  "current_team": {
    "team_number": 10,
    "owner": "Jayden",
    "team_name": "Niner Nation",
    "player_col": 19,
    "position_col": 20
  },
  "draft_state": {
    "total_picks": 190,
    "total_teams": 10,
    "completed_rounds": 19,
    "current_round": 20
  },
  "available_players": []
}